{
  "date": "2026-07-09",
  "dateFormatted": "2026年7月9日",
  "episodeImage": "https://p2.img.cctvpic.com/photoAlbum/vms/standard/img/2026/7/10/VIDE1Ys7FV3QfNXme19EvSlc260710.jpg",
  "items": [
    {
      "id": "xwlb-20260709-01",
      "date": "2026-07-09",
      "title": "习近平对福建泉州晋江市一鞋厂火灾事故作出重要指示强调 深入排查整治各类风险隐患 抓实抓细安全生产措施落实 坚决防止重特大事故发生 李强作出批示",
      "summary": "习近平对福建泉州晋江市一鞋厂火灾事故作出重要指示强调 深入排查整治各类风险隐患 抓实抓细安全生产措施落实 坚决防止重特大事故发生 李强作出批示",
      "fullContent": "习近平对福建泉州晋江市一鞋厂火灾事故作出重要指示强调 深入排查整治各类风险隐患 抓实抓细安全生产措施落实 坚决防止重特大事故发生 李强作出批示",
      "videoUrl": "https://tv.cctv.com/2026/07/10/VIDElokQ4Ud3n2k79X1s3LHC260710.shtml",
      "videoId": "ab52908d3bee45cb908ccbc9d143bdc3",
      "order": 1,
      "tags": [
        "时政",
        "领导人"
      ]
    },
    {
      "id": "xwlb-20260709-02",
      "date": "2026-07-09",
      "title": "“习近平新时代中国特色社会主义思想与世界”国际研讨会在银川举行",
      "summary": "“习近平新时代中国特色社会主义思想与世界”国际研讨会在银川举行",
      "fullContent": "“习近平新时代中国特色社会主义思想与世界”国际研讨会在银川举行",
      "videoUrl": "https://tv.cctv.com/2026/07/10/VIDElokQ4Ud3n2k79X1s3LHC260710.shtml",
      "videoId": "ab52908d3bee45cb908ccbc9d143bdc3",
      "order": 2,
      "tags": [
        "时政",
        "领导人",
        "国际"
      ]
    },
    {
      "id": "xwlb-20260709-03",
      "date": "2026-07-09",
      "title": "勇攀世界科学高峰 为建设科技强国多立新功——习近平总书记在国家科学技术奖励大会 两院院士大会 中国科协第十一次全国代表大会上的重要讲话引发热烈反响",
      "summary": "勇攀世界科学高峰 为建设科技强国多立新功——习近平总书记在国家科学技术奖励大会 两院院士大会 中国科协第十一次全国代表大会上的重要讲话引发热烈反响",
      "fullContent": "勇攀世界科学高峰 为建设科技强国多立新功——习近平总书记在国家科学技术奖励大会 两院院士大会 中国科协第十一次全国代表大会上的重要讲话引发热烈反响",
      "videoUrl": "https://tv.cctv.com/2026/07/10/VIDElokQ4Ud3n2k79X1s3LHC260710.shtml",
      "videoId": "ab52908d3bee45cb908ccbc9d143bdc3",
      "order": 3,
      "tags": [
        "时政",
        "领导人",
        "科技"
      ]
    },
    {
      "id": "xwlb-20260709-04",
      "date": "2026-07-09",
      "title": "人民日报评论员文章：扎扎实实以科技创新支撑和引领中国式现代化——论学习贯彻习近平总书记在国家科学技术奖励大会、两院院士大会、中国科协十一大上重要讲话",
      "summary": "人民日报评论员文章：扎扎实实以科技创新支撑和引领中国式现代化——论学习贯彻习近平总书记在国家科学技术奖励大会、两院院士大会、中国科协十一大上重要讲话",
      "fullContent": "人民日报评论员文章：扎扎实实以科技创新支撑和引领中国式现代化——论学习贯彻习近平总书记在国家科学技术奖励大会、两院院士大会、中国科协十一大上重要讲话",
      "videoUrl": "https://tv.cctv.com/2026/07/10/VIDElokQ4Ud3n2k79X1s3LHC260710.shtml",
      "videoId": "ab52908d3bee45cb908ccbc9d143bdc3",
      "order": 4,
      "tags": [
        "时政",
        "领导人",
        "科技"
      ]
    },
    {
      "id": "xwlb-20260709-05",
      "date": "2026-07-09",
      "title": "中共中央办公厅、国务院办公厅印发《关于全力做好防汛抗旱工作的通知》",
      "summary": "中共中央办公厅、国务院办公厅印发《关于全力做好防汛抗旱工作的通知》",
      "fullContent": "中共中央办公厅、国务院办公厅印发《关于全力做好防汛抗旱工作的通知》",
      "videoUrl": "https://tv.cctv.com/2026/07/10/VIDElokQ4Ud3n2k79X1s3LHC260710.shtml",
      "videoId": "ab52908d3bee45cb908ccbc9d143bdc3",
      "order": 5,
      "tags": [
        "时政"
      ]
    },
    {
      "id": "xwlb-20260709-06",
      "date": "2026-07-09",
      "title": "李强会见纳米比亚总统",
      "summary": "李强会见纳米比亚总统",
      "fullContent": "李强会见纳米比亚总统",
      "videoUrl": "https://tv.cctv.com/2026/07/10/VIDElokQ4Ud3n2k79X1s3LHC260710.shtml",
      "videoId": "ab52908d3bee45cb908ccbc9d143bdc3",
      "order": 6,
      "tags": [
        "时政",
        "领导人"
      ]
    },
    {
      "id": "xwlb-20260709-07",
      "date": "2026-07-09",
      "title": "丁薛祥在两院院士大会第二次全体会议上强调 全力抓好党中央关于科技事业各项部署的落实 加快推进高水平科技自立自强",
      "summary": "丁薛祥在两院院士大会第二次全体会议上强调 全力抓好党中央关于科技事业各项部署的落实 加快推进高水平科技自立自强",
      "fullContent": "丁薛祥在两院院士大会第二次全体会议上强调 全力抓好党中央关于科技事业各项部署的落实 加快推进高水平科技自立自强",
      "videoUrl": "https://tv.cctv.com/2026/07/10/VIDElokQ4Ud3n2k79X1s3LHC260710.shtml",
      "videoId": "ab52908d3bee45cb908ccbc9d143bdc3",
      "order": 7,
      "tags": [
        "时政",
        "科技"
      ]
    },
    {
      "id": "xwlb-20260709-08",
      "date": "2026-07-09",
      "title": "美军连续两天对伊朗发动军事打击 伊朗称袭击多处美军基地 国际社会呼吁降级紧张局势 切实履行承诺",
      "summary": "美军连续两天对伊朗发动军事打击 伊朗称袭击多处美军基地 国际社会呼吁降级紧张局势 切实履行承诺",
      "fullContent": "美军连续两天对伊朗发动军事打击 伊朗称袭击多处美军基地 国际社会呼吁降级紧张局势 切实履行承诺",
      "videoUrl": "https://tv.cctv.com/2026/07/10/VIDElokQ4Ud3n2k79X1s3LHC260710.shtml",
      "videoId": "ab52908d3bee45cb908ccbc9d143bdc3",
      "order": 8,
      "tags": [
        "国际",
        "军事"
      ]
    }
  ]
}